setup.py
tkitSearch/__init__.py
tkitSearch/search.py
tkitSearch.egg-info/PKG-INFO
tkitSearch.egg-info/SOURCES.txt
tkitSearch.egg-info/dependency_links.txt
tkitSearch.egg-info/requires.txt
tkitSearch.egg-info/top_level.txt